{"nodes": [{"id": "src_app_protected_datenschutz_page_tsx", "label": "page.tsx", "file_type": "code", "source_file": "src/app/(protected)/datenschutz/page.tsx", "source_location": "L1"}, {"id": "datenschutz_page_datenschutzpage", "label": "DatenschutzPage()", "file_type": "code", "source_file": "src/app/(protected)/datenschutz/page.tsx", "source_location": "L7"}], "edges": [{"source": "src_app_protected_datenschutz_page_tsx", "target": "next", "relation": "imports_from", "context": "import", "confidence": "EXTRACTED", "source_file": "src/app/(protected)/datenschutz/page.tsx", "source_location": "L1", "weight": 1.0}, {"source": "src_app_protected_datenschutz_page_tsx", "target": "datenschutz_page_datenschutzpage", "relation": "contains", "confidence": "EXTRACTED", "source_file": "src/app/(protected)/datenschutz/page.tsx", "source_location": "L7", "weight": 1.0}], "raw_calls": [{"caller_nid": "datenschutz_page_datenschutzpage", "callee": "hierf\u00fcr", "is_member_call": false, "source_file": "src/app/(protected)/datenschutz/page.tsx", "source_location": "L30"}, {"caller_nid": "datenschutz_page_datenschutzpage", "callee": "Anwendung", "is_member_call": false, "source_file": "src/app/(protected)/datenschutz/page.tsx", "source_location": "L33"}, {"caller_nid": "datenschutz_page_datenschutzpage", "callee": "Adresse", "is_member_call": false, "source_file": "src/app/(protected)/datenschutz/page.tsx", "source_location": "L39"}, {"caller_nid": "datenschutz_page_datenschutzpage", "callee": "f", "is_member_call": true, "source_file": "src/app/(protected)/datenschutz/page.tsx", "source_location": "L45"}]}